snakemake_storage_plugin_fsspec/__init__.py
snakemake_storage_plugin_fsspec-0.1.0.dist-info/LICENSE
snakemake_storage_plugin_fsspec-0.1.0.dist-info/METADATA
snakemake_storage_plugin_fsspec-0.1.0.dist-info/WHEEL
snakemake_storage_plugin_fsspec-0.1.0.dist-info/RECORD
