Metadata-Version: 2.1
Name: snakemake-storage-plugin-fsspec
Version: 0.1.0
Summary: 
Home-page: https://github.com/snakemake/snakemake-storage-plugin-fsspec
Author: Johannes Koester
Author-email: johannes.koester@uni-due.de
Requires-Python: >=3.11,<4.0
Classifier: Programming Language :: Python :: 3
Classifier: Programming Language :: Python :: 3.11
Classifier: Programming Language :: Python :: 3.12
Requires-Dist: fsspec (>=2023.12.2,<2024.0.0)
Requires-Dist: snakemake-interface-common (>=1.15.0,<2.0.0)
Requires-Dist: snakemake-interface-storage-plugins (>=3.0.0,<4.0.0)
Requires-Dist: webdav4 (>=0.9.8,<0.10.0)
Project-URL: Documentation, https://snakemake.github.io/snakemake-plugin-catalog/plugins/storage/fsspec.html
Project-URL: Repository, https://github.com/snakemake/snakemake-storage-plugin-fsspec
